mersal/__init__.py
mersal/app.py
mersal/py.typed
mersal/_activation/builtin_handler_activator.py
mersal/_activation/handler_activator.py
mersal/activation/__init__.py
mersal/configuration/__init__.py
mersal/configuration/default_plugin.py
mersal/configuration/dependency_resolver.py
mersal/configuration/standard_configurator.py
mersal/exceptions/__init__.py
mersal/exceptions/base_exceptions.py
mersal/handlers/__init__.py
mersal/handlers/message_handler.py
mersal/idempotency/__init__.py
mersal/idempotency/config.py
mersal/idempotency/const.py
mersal/idempotency/idempotency_checker_step.py
mersal/idempotency/message_tracker.py
mersal/idempotency/plugin.py
mersal/lifespan/__init__.py
mersal/lifespan/default_lifespan_handler.py
mersal/lifespan/lifespan_handler.py
mersal/lifespan/lifespan_hooks_registration_plugin.py
mersal/lifespan/autosubscribe/__init__.py
mersal/lifespan/autosubscribe/autosubscribe_plugin.py
mersal/messages/__init__.py
mersal/messages/batch_message.py
mersal/messages/logical_message.py
mersal/messages/message_completed_event.py
mersal/messages/message_completed_event_publisher.py
mersal/messages/message_headers.py
mersal/messages/transport_message.py
mersal/outbox/__init__.py
mersal/outbox/config.py
mersal/outbox/outbox_forwarder.py
mersal/outbox/outbox_incoming_step.py
mersal/outbox/outbox_message.py
mersal/outbox/outbox_message_batch.py
mersal/outbox/outbox_storage.py
mersal/outbox/outbox_transport_decorator.py
mersal/outbox/plugin.py
mersal/outbox/in_memory/__init__.py
mersal/outbox/in_memory/in_memory_outbox_storage.py
mersal/persistence/in_memory/__init__.py
mersal/persistence/in_memory/in_memory_message_tracker.py
mersal/persistence/in_memory/in_memory_saga_storage.py
mersal/persistence/in_memory/in_memory_subscription_storage.py
mersal/persistence/not_implemented/__init__.py
mersal/persistence/not_implemented/not_implemented_subscription_storage.py
mersal/pipeline/__init__.py
mersal/pipeline/default_pipeline.py
mersal/pipeline/incoming_step.py
mersal-0.1.0.dist-info/METADATA
mersal-0.1.0.dist-info/WHEEL
mersal-0.1.0.dist-info/RECORD
