Metadata-Version: 2.4
Name: mersal
Version: 0.1.0
Summary: A service bus library.
Author-email: Abdulhaq Emhemmed <abdulhaq.emhemmed@gmail.com>
Requires-Python: >=3.10
Requires-Dist: anyio>=4.8.0
